gan/__init__.py
gan/shell/__init__.py
gan/shell/usage.py
gan/src/temp.txt
package_name/__init__.py
package_name/shell/__init__.py
package_name/shell/usage.py
package_name/src/temp.txt
gan-0.0.1.dist-info/LICENSE
gan-0.0.1.dist-info/METADATA
gan-0.0.1.dist-info/WHEEL
gan-0.0.1.dist-info/entry_points.txt
gan-0.0.1.dist-info/top_level.txt
gan-0.0.1.dist-info/zip-safe
gan-0.0.1.dist-info/RECORD
